flake8_if_checker.py
flake8_if_checker-0.3.0.dist-info/LICENSE
flake8_if_checker-0.3.0.dist-info/METADATA
flake8_if_checker-0.3.0.dist-info/WHEEL
flake8_if_checker-0.3.0.dist-info/entry_points.txt
flake8_if_checker-0.3.0.dist-info/top_level.txt
flake8_if_checker-0.3.0.dist-info/RECORD
