Metadata-Version: 2.1
Name: flake8-if-checker
Version: 0.3.0
Summary: Flake8's IF statement complexity linter plugin
Home-page: https://github.com/danie1k/python-flake8-if-checker
Author: Daniel Kuruc
Author-email: daniel@kuruc.dev
License: MIT
Project-URL: Code, https://github.com/danie1k/python-flake8-if-checker
Project-URL: Issue tracker, https://github.com/danie1k/python-flake8-if-checker/issues
Keywords: pep8 flake8 conditional complexity
Platform: UNKNOWN
Classifier: Development Status :: 4 - Beta
Classifier: Environment :: Console
Classifier: Framework :: Flake8
Classifier: Intended Audience :: Developers
Classifier: License :: OSI Approved :: MIT License
Classifier: Operating System :: OS Independent
Classifier: Programming Language :: Python
Classifier: Programming Language :: Python :: 2
Classifier: Programming Language :: Python :: 2.7
Classifier: Programming Language :: Python :: 3
Classifier: Programming Language :: Python :: 3.5
Classifier: Programming Language :: Python :: 3.6
Classifier: Programming Language :: Python :: 3.7
Classifier: Programming Language :: Python :: 3.8
Classifier: Topic :: Software Development :: Libraries :: Python Modules
Classifier: Topic :: Software Development :: Quality Assurance
Requires-Python: >=2.7, <3.9
Requires-Dist: flake8 (>3.2.0)
Provides-Extra: lint
Requires-Dist: flake8 (>=3.0.0) ; extra == 'lint'
Requires-Dist: isort (>=4.3.0) ; extra == 'lint'
Requires-Dist: pylint (>=1.9.0) ; extra == 'lint'
Provides-Extra: py3lint
Requires-Dist: black (>=18.6b2) ; extra == 'py3lint'
Requires-Dist: mypy (>=0.790) ; extra == 'py3lint'
Requires-Dist: typing ; extra == 'py3lint'
Provides-Extra: tests
Requires-Dist: coverage (>=5.0) ; extra == 'tests'
Requires-Dist: mock ; extra == 'tests'
Requires-Dist: pytest (>=4.6.0) ; extra == 'tests'
Requires-Dist: pytest-sugar ; extra == 'tests'
